Workbook

Sheet Input
A1: INPUT & ASUMSI - Proyeksi Merchant Seato Y2-Y5 (not final)
A2: Legenda: biru = angka input (hardcode) | hitam = formula | kuning = ASUMSI BARU dari analisis ini (belum divalidasi) | tanpa kuning = diambil dari file FOS.
A4: Parameter | B4: Nilai | C4: Satuan | D4: Sumber / status
A6: Merchant awal (Y1 M1) | B6: 50 | C6: merchant | D6: File FOS, Growth Projection Y1 M1
A7: Merchant Y1 M11 | B7: 300 | C7: merchant | D7: File FOS, Growth Projection Y1 M11
A8: Merchant Y1 M12 (titik awal proyeksi, N0) | B8: 340 | C8: merchant | D8: File FOS, Growth Projection Y1 M12
A9: Growth bulanan terakhir Y1 (M11 ke M12) | B9: =B8/B7-1 | C9: per bulan | D9: Formula dari file FOS
A10: Growth rata-rata Y1 (CAGR bulanan M1-M12) | B10: =(B8/B6)^(1/11)-1 | C10: per bulan | D10: Formula dari file FOS
A11: Churn merchant bulanan | B11: 0.15 | C11: per bulan | D11: Retention 85% dari file FOS; diartikan BULANAN (konfirmasi pengguna)
A12: Plafon pasar K - Low (Bandung+Jakarta) | B12: 1500 | C12: merchant | D12: ASUMSI. SAM Jakarta belum tervalidasi (lihat sheet Sumber)
A13: Plafon pasar K - Mid | B13: 3000 | C13: merchant | D13: ASUMSI. Sama seperti di atas
A14: Plafon pasar K - High | B14: 5000 | C14: merchant | D14: ASUMSI. Sama seperti di atas
A15: Skenario aktif untuk sheet BiayaRevenue (1=Low, 2=Mid, 3=High) | B15: 2 | C15: pilih 1-3 | D15: Ubah angka ini untuk ganti skenario
A16: Komposisi Starter | B16: 0.3 | D16: File FOS, Pricing
A17: Komposisi Professional | B17: 0.5 | D17: File FOS, Pricing
A18: Komposisi Enterprise | B18: 0.2 | D18: File FOS, Pricing
A19: Harga Starter | B19: 299000 | C19: per bulan | D19: File FOS, Pricing (not final)
A20: Harga Professional | B20: 599000 | C20: per bulan | D20: File FOS, Pricing (not final)
A21: Harga Enterprise | B21: 799000 | C21: per bulan | D21: File FOS, Pricing (not final)
A22: Promotion purchase rate | B22: 0.3 | D22: File FOS, Key Assumption
A23: Unit impression per merchant yang beli promo (10.000 views / 1.000) | B23: 10 | C23: unit CPM | D23: File FOS: 10.000 views/bulan, konstan (tidak tumbuh)
A24: Rata-rata biaya promosi (CPM) | B24: 16250 | C24: per 1.000 views | D24: File FOS, Avg. Promotion Cost
A25: ARPM subscription | B25: =B16*B19+B17*B20+B18*B21 | C25: per merchant/bulan | D25: Formula; semua merchant dianggap bayar penuh
A26: ARPM promosi | B26: =B22*B23*B24 | C26: per merchant/bulan | D26: Formula
A27: ARPM total | B27: =B25+B26 | C27: per merchant/bulan | D27: Cocok dengan Rp597.750 di Revenue Model FOS
A28: CAC merchant | B28: 200000 | C28: per merchant | D28: File FOS, Key Assumption
A29: Kapasitas onboarding per sales | B29: 40 | C29: merchant/bulan | D29: Diturunkan dari CAC M12 Rp8 jt / Rp200 rb = 40 (hanya bukti kapasitas di file)
A30: Gaji sales/marketer | B30: 10000000 | C30: per orang/bulan | D30: File FOS, Cost Structure
A31: ARPM (Yr1) di tab KPI file FOS | B31: 699000 | C31: per bulan | D31: File FOS, KPI (tidak cocok dengan Revenue Model)
A32: Est. LTV di tab KPI file FOS | B32: 12582000 | D32: File FOS, KPI

Sheet Proyeksi
A1: PROYEKSI MERCHANT Y2-Y5 (bulanan): Logistik vs Eksponensial (not final)
A2: Plafon K | D2: =Input!$B$12 | E2: =Input!$B$13 | F2: =Input!$B$14 | G2: tanpa plafon | H2: tanpa plafon
A3: Laju r (dikalibrasi agar growth bulan pertama = growth M12 Y1) | D3: =Input!$B$9/(1-Input!$B$8/D2) | E3: =Input!$B$9/(1-Input!$B$8/E2) | F3: =Input!$B$9/(1-Input!$B$8/F2) | G3: =Input!$B$10 | H3: =Input!$B$9
A5: Year | B5: Bulan | C5: t (bln sejak Y1 M12) | D5: Logistik Low | E5: Logistik Mid | F5: Logistik High | G5: Eksponensial (growth rata-rata Y1) | H5: Eksponensial (growth M12 Y1)
A6: 1 | B6: 12 | C6: 0 | D6: =Input!$B$8 | E6: =Input!$B$8 | F6: =Input!$B$8 | G6: =Input!$B$8 | H6: =Input!$B$8
A7: =INT((C7-1)/12)+2 | B7: =MOD(C7-1,12)+1 | C7: 1 | D7: =D6+D$3*D6*(1-D6/D$2) | E7: =E6+E$3*E6*(1-E6/E$2) | F7: =F6+F$3*F6*(1-F6/F$2) | G7: =G6*(1+G$3) | H7: =H6*(1+H$3)
A8: =INT((C8-1)/12)+2 | B8: =MOD(C8-1,12)+1 | C8: 2 | D8: =D7+D$3*D7*(1-D7/D$2) | E8: =E7+E$3*E7*(1-E7/E$2) | F8: =F7+F$3*F7*(1-F7/F$2) | G8: =G7*(1+G$3) | H8: =H7*(1+H$3)
A9: =INT((C9-1)/12)+2 | B9: =MOD(C9-1,12)+1 | C9: 3 | D9: =D8+D$3*D8*(1-D8/D$2) | E9: =E8+E$3*E8*(1-E8/E$2) | F9: =F8+F$3*F8*(1-F8/F$2) | G9: =G8*(1+G$3) | H9: =H8*(1+H$3)
A10: =INT((C10-1)/12)+2 | B10: =MOD(C10-1,12)+1 | C10: 4 | D10: =D9+D$3*D9*(1-D9/D$2) | E10: =E9+E$3*E9*(1-E9/E$2) | F10: =F9+F$3*F9*(1-F9/F$2) | G10: =G9*(1+G$3) | H10: =H9*(1+H$3)
A11: =INT((C11-1)/12)+2 | B11: =MOD(C11-1,12)+1 | C11: 5 | D11: =D10+D$3*D10*(1-D10/D$2) | E11: =E10+E$3*E10*(1-E10/E$2) | F11: =F10+F$3*F10*(1-F10/F$2) | G11: =G10*(1+G$3) | H11: =H10*(1+H$3)
A12: =INT((C12-1)/12)+2 | B12: =MOD(C12-1,12)+1 | C12: 6 | D12: =D11+D$3*D11*(1-D11/D$2) | E12: =E11+E$3*E11*(1-E11/E$2) | F12: =F11+F$3*F11*(1-F11/F$2) | G12: =G11*(1+G$3) | H12: =H11*(1+H$3)
A13: =INT((C13-1)/12)+2 | B13: =MOD(C13-1,12)+1 | C13: 7 | D13: =D12+D$3*D12*(1-D12/D$2) | E13: =E12+E$3*E12*(1-E12/E$2) | F13: =F12+F$3*F12*(1-F12/F$2) | G13: =G12*(1+G$3) | H13: =H12*(1+H$3)
A14: =INT((C14-1)/12)+2 | B14: =MOD(C14-1,12)+1 | C14: 8 | D14: =D13+D$3*D13*(1-D13/D$2) | E14: =E13+E$3*E13*(1-E13/E$2) | F14: =F13+F$3*F13*(1-F13/F$2) | G14: =G13*(1+G$3) | H14: =H13*(1+H$3)
A15: =INT((C15-1)/12)+2 | B15: =MOD(C15-1,12)+1 | C15: 9 | D15: =D14+D$3*D14*(1-D14/D$2) | E15: =E14+E$3*E14*(1-E14/E$2) | F15: =F14+F$3*F14*(1-F14/F$2) | G15: =G14*(1+G$3) | H15: =H14*(1+H$3)
A16: =INT((C16-1)/12)+2 | B16: =MOD(C16-1,12)+1 | C16: 10 | D16: =D15+D$3*D15*(1-D15/D$2) | E16: =E15+E$3*E15*(1-E15/E$2) | F16: =F15+F$3*F15*(1-F15/F$2) | G16: =G15*(1+G$3) | H16: =H15*(1+H$3)
A17: =INT((C17-1)/12)+2 | B17: =MOD(C17-1,12)+1 | C17: 11 | D17: =D16+D$3*D16*(1-D16/D$2) | E17: =E16+E$3*E16*(1-E16/E$2) | F17: =F16+F$3*F16*(1-F16/F$2) | G17: =G16*(1+G$3) | H17: =H16*(1+H$3)
A18: =INT((C18-1)/12)+2 | B18: =MOD(C18-1,12)+1 | C18: 12 | D18: =D17+D$3*D17*(1-D17/D$2) | E18: =E17+E$3*E17*(1-E17/E$2) | F18: =F17+F$3*F17*(1-F17/F$2) | G18: =G17*(1+G$3) | H18: =H17*(1+H$3)
... A54: =INT((C54-1)/12)+2 | B54: =MOD(C54-1,12)+1 | C54: 48 | D54: =D53+D$3*D53*(1-D53/D$2) | E54: =E53+E$3*E53*(1-E53/E$2) | F54: =F53+F$3*F53*(1-F53/F$2) | G54: =G53*(1+G$3) | H54: =H53*(1+H$3)
A56: Logistik: N(t+1) = N(t) + r x N(t) x (1 - N(t)/K). Eksponensial: N(t+1) = N(t) x (1+g). Baris t=0 = Y1 M12 (340, dari file FOS). Semua nilai di Y2-Y5 adalah PROYEKSI, bukan data.

Sheet EksVsLogistik
A1: EKSPONENSIAL vs LOGISTIK + CEK Y1 DARI FILE (not final)
A3: A. Merchant akhir tahun per skenario
A4: Seri | B4: Akhir Y1 | C4: Akhir Y2 | D4: Akhir Y3 | E4: Akhir Y4 | F4: Akhir Y5
A5: Logistik Low | B5: =INDEX(Proyeksi!$D$6:$D$54,0+1) | C5: =INDEX(Proyeksi!$D$6:$D$54,12+1) | D5: =INDEX(Proyeksi!$D$6:$D$54,24+1) | E5: =INDEX(Proyeksi!$D$6:$D$54,36+1) | F5: =INDEX(Proyeksi!$D$6:$D$54,48+1)
A6: Logistik Mid | B6: =INDEX(Proyeksi!$E$6:$E$54,0+1) | C6: =INDEX(Proyeksi!$E$6:$E$54,12+1) | D6: =INDEX(Proyeksi!$E$6:$E$54,24+1) | E6: =INDEX(Proyeksi!$E$6:$E$54,36+1) | F6: =INDEX(Proyeksi!$E$6:$E$54,48+1)
A7: Logistik High | B7: =INDEX(Proyeksi!$F$6:$F$54,0+1) | C7: =INDEX(Proyeksi!$F$6:$F$54,12+1) | D7: =INDEX(Proyeksi!$F$6:$F$54,24+1) | E7: =INDEX(Proyeksi!$F$6:$F$54,36+1) | F7: =INDEX(Proyeksi!$F$6:$F$54,48+1)
A8: Eksponensial (growth rata-rata Y1) | B8: =INDEX(Proyeksi!$G$6:$G$54,0+1) | C8: =INDEX(Proyeksi!$G$6:$G$54,12+1) | D8: =INDEX(Proyeksi!$G$6:$G$54,24+1) | E8: =INDEX(Proyeksi!$G$6:$G$54,36+1) | F8: =INDEX(Proyeksi!$G$6:$G$54,48+1)
A9: Eksponensial (growth M12 Y1) | B9: =INDEX(Proyeksi!$H$6:$H$54,0+1) | C9: =INDEX(Proyeksi!$H$6:$H$54,12+1) | D9: =INDEX(Proyeksi!$H$6:$H$54,24+1) | E9: =INDEX(Proyeksi!$H$6:$H$54,36+1) | F9: =INDEX(Proyeksi!$H$6:$H$54,48+1)
A10: Eksponensial rata-rata Y1 / Plafon Mid (x) | B10: =B8/Input!$B$13 | C10: =C8/Input!$B$13 | D10: =D8/Input!$B$13 | E10: =E8/Input!$B$13 | F10: =F8/Input!$B$13
A11: Eksponensial M12 Y1 / Plafon Mid (x) | B11: =B9/Input!$B$13 | C11: =C9/Input!$B$13 | D11: =D9/Input!$B$13 | E11: =E9/Input!$B$13 | F11: =F9/Input!$B$13
A12: Melebihi plafon Mid? (rata-rata Y1) | B12: =IF(B8>Input!$B$13,"YA","tidak") | C12: =IF(C8>Input!$B$13,"YA","tidak") | D12: =IF(D8>Input!$B$13,"YA","tidak") | E12: =IF(E8>Input!$B$13,"YA","tidak") | F12: =IF(F8>Input!$B$13,"YA","tidak")
A15: B. Cek Year 1 dari file FOS: apakah churn 15%/bulan dihitung?
A16: Bulan Y1 | B16: Merchant (file) | C16: Growth bulanan | D16: Net adds (file) | E16: Churn (15% x merchant bulan lalu) | F16: Gross adds yg dibutuhkan | G16: CAC di file (net adds x Rp200rb) | H16: CAC jika churn dihitung
A17: M1 | B17: 50 | C17: - | D17: =B17 | E17: 0 | F17: =D17+E17 | G17: =D17*Input!$B$28 | H17: =F17*Input!$B$28
A18: M2 | B18: 65 | C18: =B18/B17-1 | D18: =B18-B17 | E18: =Input!$B$11*B17 | F18: =D18+E18 | G18: =D18*Input!$B$28 | H18: =F18*Input!$B$28
A19: M3 | B19: 82 | C19: =B19/B18-1 | D19: =B19-B18 | E19: =Input!$B$11*B18 | F19: =D19+E19 | G19: =D19*Input!$B$28 | H19: =F19*Input!$B$28
A20: M4 | B20: 100 | C20: =B20/B19-1 | D20: =B20-B19 | E20: =Input!$B$11*B19 | F20: =D20+E20 | G20: =D20*Input!$B$28 | H20: =F20*Input!$B$28
A21: M5 | B21: 120 | C21: =B21/B20-1 | D21: =B21-B20 | E21: =Input!$B$11*B20 | F21: =D21+E21 | G21: =D21*Input!$B$28 | H21: =F21*Input!$B$28
A22: M6 | B22: 145 | C22: =B22/B21-1 | D22: =B22-B21 | E22: =Input!$B$11*B21 | F22: =D22+E22 | G22: =D22*Input!$B$28 | H22: =F22*Input!$B$28
A23: M7 | B23: 170 | C23: =B23/B22-1 | D23: =B23-B22 | E23: =Input!$B$11*B22 | F23: =D23+E23 | G23: =D23*Input!$B$28 | H23: =F23*Input!$B$28
A24: M8 | B24: 200 | C24: =B24/B23-1 | D24: =B24-B23 | E24: =Input!$B$11*B23 | F24: =D24+E24 | G24: =D24*Input!$B$28 | H24: =F24*Input!$B$28
A25: M9 | B25: 230 | C25: =B25/B24-1 | D25: =B25-B24 | E25: =Input!$B$11*B24 | F25: =D25+E25 | G25: =D25*Input!$B$28 | H25: =F25*Input!$B$28
A26: M10 | B26: 265 | C26: =B26/B25-1 | D26: =B26-B25 | E26: =Input!$B$11*B25 | F26: =D26+E26 | G26: =D26*Input!$B$28 | H26: =F26*Input!$B$28
A27: M11 | B27: 300 | C27: =B27/B26-1 | D27: =B27-B26 | E27: =Input!$B$11*B26 | F27: =D27+E27 | G27: =D27*Input!$B$28 | H27: =F27*Input!$B$28
A28: M12 | B28: 340 | C28: =B28/B27-1 | D28: =B28-B27 | E28: =Input!$B$11*B27 | F28: =D28+E28 | G28: =D28*Input!$B$28 | H28: =F28*Input!$B$28
A29: TOTAL | D29: =SUM(D17:D28) | E29: =SUM(E17:E28) | F29: =SUM(F17:F28) | G29: =SUM(G17:G28) | H29: =SUM(H17:H28)
A30: Selisih CAC (churn dihitung vs file) | G30: =H29-G29 | H30: =H29/G29-1
A31: Cek: total CAC file harus = Rp68.000.000 (Cost Structure FOS, Merchant CAC).
A33: C. Plafon merchant yang bisa dipertahankan dengan churn tetap
A34: Adds/bulan maksimum Y1 (file, M12) | B34: =D28
A35: Plafon steady-state = adds / churn | B35: =B34/Input!$B$11
A36: Target merchant akhir Y1 di file | B36: =Input!$B$8
A37: Churn bulanan agar 40 adds/bulan bisa menopang 340 merchant | B37: =B34/B36
A38: Catatan: dengan churn 15%/bulan, 40 adds/bulan hanya cukup menopang ~267 merchant. Angka 340 di file hanya tercapai jika churn ~12% atau adds lebih besar.

Sheet BiayaRevenue
A1: BIAYA AKUISISI & REVENUE untuk skenario aktif (not final)
A2: Skenario aktif: | B2: =CHOOSE(Input!$B$15,"Low","Mid","High")&" (K="&TEXT(INDEX(Proyeksi!$D$2:$F$2,Input!$B$15),"#,##0")&")"
A3: Ubah di Input!B15. Hanya biaya akuisisi (CAC) + gaji sales yang dihitung di sini; biaya lain (tim inti, server, marketing, dsb.) tidak termasuk. Semua merchant dianggap membayar penuh (tanpa trial).
A5: Ringkasan per tahun | B5: Year 2 | C5: Year 3 | D5: Year 4 | E5: Year 5
A6: Merchant akhir tahun | B6: =INDEX($D$18:$D$65,12) | C6: =INDEX($D$18:$D$65,24) | D6: =INDEX($D$18:$D$65,36) | E6: =INDEX($D$18:$D$65,48)
A7: Total gross adds (net adds + pengganti churn) | B7: =SUMIFS($G$18:$G$65,$A$18:$A$65,2) | C7: =SUMIFS($G$18:$G$65,$A$18:$A$65,3) | D7: =SUMIFS($G$18:$G$65,$A$18:$A$65,4) | E7: =SUMIFS($G$18:$G$65,$A$18:$A$65,5)
A8: Rata-rata gross adds per bulan | B8: =B7/12 | C8: =C7/12 | D8: =D7/12 | E8: =E7/12
A9: Biaya CAC | B9: =SUMIFS($H$18:$H$65,$A$18:$A$65,2) | C9: =SUMIFS($H$18:$H$65,$A$18:$A$65,3) | D9: =SUMIFS($H$18:$H$65,$A$18:$A$65,4) | E9: =SUMIFS($H$18:$H$65,$A$18:$A$65,5)
A10: Sales yang dibutuhkan (maks. bulanan) | B10: =MAX(INDEX($I$18:$I$65,1):INDEX($I$18:$I$65,12)) | C10: =MAX(INDEX($I$18:$I$65,13):INDEX($I$18:$I$65,24)) | D10: =MAX(INDEX($I$18:$I$65,25):INDEX($I$18:$I$65,36)) | E10: =MAX(INDEX($I$18:$I$65,37):INDEX($I$18:$I$65,48))
A11: Biaya gaji sales | B11: =SUMIFS($J$18:$J$65,$A$18:$A$65,2) | C11: =SUMIFS($J$18:$J$65,$A$18:$A$65,3) | D11: =SUMIFS($J$18:$J$65,$A$18:$A$65,4) | E11: =SUMIFS($J$18:$J$65,$A$18:$A$65,5)
A12: Revenue (merchant x ARPM) | B12: =SUMIFS($K$18:$K$65,$A$18:$A$65,2) | C12: =SUMIFS($K$18:$K$65,$A$18:$A$65,3) | D12: =SUMIFS($K$18:$K$65,$A$18:$A$65,4) | E12: =SUMIFS($K$18:$K$65,$A$18:$A$65,5)
A13: Revenue - CAC - gaji sales | B13: =B12-B9-B11 | C13: =C12-C9-C11 | D13: =D12-D9-D11 | E13: =E12-E9-E11
A15: Pembanding: CAC Y1 di file = Rp68.000.000 (tanpa churn) | dengan churn 15%/bulan lihat EksVsLogistik!H29.
A17: Year | B17: Bulan | C17: t | D17: Merchant akhir bulan | E17: Net adds | F17: Churn (pengganti) | G17: Gross adds | H17: Biaya CAC | I17: Sales dibutuhkan | J17: Gaji sales | K17: Revenue | L17: Revenue - CAC - gaji
A18: =Proyeksi!A7 | B18: =Proyeksi!B7 | C18: =Proyeksi!C7 | D18: =INDEX(Proyeksi!$D7:$F7,Input!$B$15) | E18: =D18-INDEX(Proyeksi!$D6:$F6,Input!$B$15) | F18: =Input!$B$11*INDEX(Proyeksi!$D6:$F6,Input!$B$15) | G18: =E18+F18 | H18: =G18*Input!$B$28 | I18: =MAX(1,ROUNDUP(G18/Input!$B$29,0)) | J18: =I18*Input!$B$30 | K18: =D18*Input!$B$27 | L18: =K18-H18-J18
A19: =Proyeksi!A8 | B19: =Proyeksi!B8 | C19: =Proyeksi!C8 | D19: =INDEX(Proyeksi!$D8:$F8,Input!$B$15) | E19: =D19-INDEX(Proyeksi!$D7:$F7,Input!$B$15) | F19: =Input!$B$11*INDEX(Proyeksi!$D7:$F7,Input!$B$15) | G19: =E19+F19 | H19: =G19*Input!$B$28 | I19: =MAX(1,ROUNDUP(G19/Input!$B$29,0)) | J19: =I19*Input!$B$30 | K19: =D19*Input!$B$27 | L19: =K19-H19-J19
A20: =Proyeksi!A9 | B20: =Proyeksi!B9 | C20: =Proyeksi!C9 | D20: =INDEX(Proyeksi!$D9:$F9,Input!$B$15) | E20: =D20-INDEX(Proyeksi!$D8:$F8,Input!$B$15) | F20: =Input!$B$11*INDEX(Proyeksi!$D8:$F8,Input!$B$15) | G20: =E20+F20 | H20: =G20*Input!$B$28 | I20: =MAX(1,ROUNDUP(G20/Input!$B$29,0)) | J20: =I20*Input!$B$30 | K20: =D20*Input!$B$27 | L20: =K20-H20-J20
A21: =Proyeksi!A10 | B21: =Proyeksi!B10 | C21: =Proyeksi!C10 | D21: =INDEX(Proyeksi!$D10:$F10,Input!$B$15) | E21: =D21-INDEX(Proyeksi!$D9:$F9,Input!$B$15) | F21: =Input!$B$11*INDEX(Proyeksi!$D9:$F9,Input!$B$15) | G21: =E21+F21 | H21: =G21*Input!$B$28 | I21: =MAX(1,ROUNDUP(G21/Input!$B$29,0)) | J21: =I21*Input!$B$30 | K21: =D21*Input!$B$27 | L21: =K21-H21-J21
A22: =Proyeksi!A11 | B22: =Proyeksi!B11 | C22: =Proyeksi!C11 | D22: =INDEX(Proyeksi!$D11:$F11,Input!$B$15) | E22: =D22-INDEX(Proyeksi!$D10:$F10,Input!$B$15) | F22: =Input!$B$11*INDEX(Proyeksi!$D10:$F10,Input!$B$15) | G22: =E22+F22 | H22: =G22*Input!$B$28 | I22: =MAX(1,ROUNDUP(G22/Input!$B$29,0)) | J22: =I22*Input!$B$30 | K22: =D22*Input!$B$27 | L22: =K22-H22-J22
A23: =Proyeksi!A12 | B23: =Proyeksi!B12 | C23: =Proyeksi!C12 | D23: =INDEX(Proyeksi!$D12:$F12,Input!$B$15) | E23: =D23-INDEX(Proyeksi!$D11:$F11,Input!$B$15) | F23: =Input!$B$11*INDEX(Proyeksi!$D11:$F11,Input!$B$15) | G23: =E23+F23 | H23: =G23*Input!$B$28 | I23: =MAX(1,ROUNDUP(G23/Input!$B$29,0)) | J23: =I23*Input!$B$30 | K23: =D23*Input!$B$27 | L23: =K23-H23-J23
A24: =Proyeksi!A13 | B24: =Proyeksi!B13 | C24: =Proyeksi!C13 | D24: =INDEX(Proyeksi!$D13:$F13,Input!$B$15) | E24: =D24-INDEX(Proyeksi!$D12:$F12,Input!$B$15) | F24: =Input!$B$11*INDEX(Proyeksi!$D12:$F12,Input!$B$15) | G24: =E24+F24 | H24: =G24*Input!$B$28 | I24: =MAX(1,ROUNDUP(G24/Input!$B$29,0)) | J24: =I24*Input!$B$30 | K24: =D24*Input!$B$27 | L24: =K24-H24-J24
A25: =Proyeksi!A14 | B25: =Proyeksi!B14 | C25: =Proyeksi!C14 | D25: =INDEX(Proyeksi!$D14:$F14,Input!$B$15) | E25: =D25-INDEX(Proyeksi!$D13:$F13,Input!$B$15) | F25: =Input!$B$11*INDEX(Proyeksi!$D13:$F13,Input!$B$15) | G25: =E25+F25 | H25: =G25*Input!$B$28 | I25: =MAX(1,ROUNDUP(G25/Input!$B$29,0)) | J25: =I25*Input!$B$30 | K25: =D25*Input!$B$27 | L25: =K25-H25-J25
A26: =Proyeksi!A15 | B26: =Proyeksi!B15 | C26: =Proyeksi!C15 | D26: =INDEX(Proyeksi!$D15:$F15,Input!$B$15) | E26: =D26-INDEX(Proyeksi!$D14:$F14,Input!$B$15) | F26: =Input!$B$11*INDEX(Proyeksi!$D14:$F14,Input!$B$15) | G26: =E26+F26 | H26: =G26*Input!$B$28 | I26: =MAX(1,ROUNDUP(G26/Input!$B$29,0)) | J26: =I26*Input!$B$30 | K26: =D26*Input!$B$27 | L26: =K26-H26-J26
A27: =Proyeksi!A16 | B27: =Proyeksi!B16 | C27: =Proyeksi!C16 | D27: =INDEX(Proyeksi!$D16:$F16,Input!$B$15) | E27: =D27-INDEX(Proyeksi!$D15:$F15,Input!$B$15) | F27: =Input!$B$11*INDEX(Proyeksi!$D15:$F15,Input!$B$15) | G27: =E27+F27 | H27: =G27*Input!$B$28 | I27: =MAX(1,ROUNDUP(G27/Input!$B$29,0)) | J27: =I27*Input!$B$30 | K27: =D27*Input!$B$27 | L27: =K27-H27-J27
A28: =Proyeksi!A17 | B28: =Proyeksi!B17 | C28: =Proyeksi!C17 | D28: =INDEX(Proyeksi!$D17:$F17,Input!$B$15) | E28: =D28-INDEX(Proyeksi!$D16:$F16,Input!$B$15) | F28: =Input!$B$11*INDEX(Proyeksi!$D16:$F16,Input!$B$15) | G28: =E28+F28 | H28: =G28*Input!$B$28 | I28: =MAX(1,ROUNDUP(G28/Input!$B$29,0)) | J28: =I28*Input!$B$30 | K28: =D28*Input!$B$27 | L28: =K28-H28-J28
A29: =Proyeksi!A18 | B29: =Proyeksi!B18 | C29: =Proyeksi!C18 | D29: =INDEX(Proyeksi!$D18:$F18,Input!$B$15) | E29: =D29-INDEX(Proyeksi!$D17:$F17,Input!$B$15) | F29: =Input!$B$11*INDEX(Proyeksi!$D17:$F17,Input!$B$15) | G29: =E29+F29 | H29: =G29*Input!$B$28 | I29: =MAX(1,ROUNDUP(G29/Input!$B$29,0)) | J29: =I29*Input!$B$30 | K29: =D29*Input!$B$27 | L29: =K29-H29-J29
... A65: =Proyeksi!A54 | B65: =Proyeksi!B54 | C65: =Proyeksi!C54 | D65: =INDEX(Proyeksi!$D54:$F54,Input!$B$15) | E65: =D65-INDEX(Proyeksi!$D53:$F53,Input!$B$15) | F65: =Input!$B$11*INDEX(Proyeksi!$D53:$F53,Input!$B$15) | G65: =E65+F65 | H65: =G65*Input!$B$28 | I65: =MAX(1,ROUNDUP(G65/Input!$B$29,0)) | J65: =I65*Input!$B$30 | K65: =D65*Input!$B$27 | L65: =K65-H65-J65

Sheet Temuan
A1: TEMUAN / GAP di file FOS yang mempengaruhi proyeksi (not final)
A3: No | B3: Temuan | C3: Bukti (di file FOS) | D3: Angka | E3: Saran
A4: 1 | B4: CAC Y1 mengasumsikan churn nol | C4: Cost Structure: Merchant CAC M2..M12 = net adds x Rp200rb (mis. M2 Rp3jt = 15 merchant). Key Assumption: retention 85%. | D4: ="CAC file "&TEXT(EksVsLogistik!G29,"#,##0")&" vs dengan churn "&TEXT(EksVsLogistik!H29,"#,##0")&" (+"&TEXT(EksVsLogistik!H30,"0%")&")" | E4: Hitung CAC dari gross adds, bukan net adds. Revisi Cost Structure dan raise.
A5: 2 | B5: 40 adds/bulan hanya menopang ~267 merchant | C5: Cost Structure: CAC M12 Rp8jt = 40 merchant. Churn 15%/bulan. | D5: ="Plafon steady-state = "&TEXT(EksVsLogistik!B35,"#,##0")&" merchant (target 340)" | E5: Turunkan churn atau naikkan kapasitas akuisisi.
A6: 3 | B6: Est. LTV Rp12.582.000 tidak bisa direproduksi | C6: Tab KPI: ARPM 699.000, Retention 0,85, Est. LTV 12.582.000 = 699.000 x 18. | D6: ="Implisit "&TEXT(Input!B32/Input!B31,"0.0")&" bulan; umur dari churn 15% = "&TEXT(1/Input!B11,"0.0")&" bulan; LTV jika ARPM 597.750 = "&TEXT(Input!B27/Input!B11,"#,##0") | E6: Definisikan rumus LTV (ARPM x umur) dan pakai churn yang sama dengan proyeksi.
A7: 4 | B7: ARPM tidak konsisten | C7: Tab KPI: ARPM Yr1 Rp699.000. Revenue Model: ARPM Rp597.750 (subscription Rp549.000 + promo Rp48.750). | D7: ="Selisih "&TEXT(Input!B31-Input!B27,"#,##0")&" per merchant/bulan" | E7: Pilih satu definisi ARPM.
A8: 5 | B8: Y2 M1 = 400 melompat dari tren | C8: Growth Projection Y2 M1 = 400; M12 Y1 = 340; growth Y1 turun 30% ke 13%. | D8: ="Growth implisit "&TEXT(400/Input!B8-1,"0.0%")&" vs 13,3% di M12" | E8: Y2 M1 sebaiknya dari kurva, bukan angka tetap.
A9: 6 | B9: Kapasitas sales tidak naik | C9: Cost Structure: 1 Salary Marketer/Sales Rp10jt konstan M1-M12. | D9: ="Sales dibutuhkan Y2 (skenario aktif): "&TEXT(BiayaRevenue!B10,"0") | E9: Tambahkan baris biaya sales Y2 dan tambah tim bertahap.
A10: 7 | B10: Raise tidak konsisten dengan klaim | C10: Capital Deployment: waterfall pakai revenue Rp332.051.950 (Model 4, turunan Model 3 = 100 merchant) sementara klaim 'Mencapai 340 merchant' dan Cashflow memakai Model 1 (Rp1,23 M). | D10: Model 1 vs Model 3: 340 vs 100 merchant | E10: Pilih satu skenario sebagai dasar raise dan konsistenkan.
A11: 8 | B11: P&L M1 subscription tidak cocok | C11: P&L M1 Rp7.117.890; Revenue Model M1 Rp27.450.000 (angka Model 4 kasus 4 terselip). | D11: Selisih Rp20.332.110 | E11: Perbaiki link P&L M1.
A12: 9 | B12: Semua merchant bayar penuh sejak M1 | C12: Revenue Model menghitung 50 merchant x tarif penuh di M1, tapi Cost Structure punya Growth Cost (Trial Subsidy) Rp2,25jt/bulan. | D12: - | E12: Tambahkan fase trial dan konversi ke berbayar.
A13: 10 | B13: Impression tidak tumbuh | C13: Key Assumption: 10.000 views/bulan 'growing exponentially', tetapi Promotion Revenue = 10 unit CPM tetap per merchant pembeli promo. | D13: Promo/merchant tetap Rp48.750 | E13: Hubungkan impression ke jumlah user (50.000 user di klaim raise).
A14: 11 | B14: Plafon pasar belum tervalidasi | C14: Lihat sheet Sumber: Bandung ~899-961; Jakarta 3 sumber saling tidak sebanding. | D14: K Low/Mid/High adalah ASUMSI | E14: Validasi SAM per kota (segmen kafe/resto lifestyle) sebelum angka K dipakai investor.

Sheet Sumber
A1: SUMBER DATA PASAR & CATATAN VALIDASI
A3: Wilayah | B3: Angka | C3: Tahun / definisi | D3: Sumber
A4: Bandung | B4: 961 | C4: 2018, restoran/rumah makan (Disbudpar Kota Bandung) | D4: https://bandungkota.bps.go.id/en/statistics-table/2/MTQ3IzI=/jumlah-rumah-makan--restoran-menurut-kecamatan.html
A5: Bandung | B5: ~899 | C5: 2022, 'café dan restoran' (hasil pencarian, dataset sumber belum dibuka) | D5: https://opendata.bandung.go.id/dataset/data-rumah-makan-restoran-cafe-di-kota-bandung
A6: DKI Jakarta | B6: 202.983 | C6: 2024, restoran dan rumah makan (kemungkinan termasuk warung) | D6: https://data.goodstats.id/statistic/10-provinsi-dengan-jumlah-restoranrumah-makan-terbanyak-5R8BM
A7: DKI Jakarta | B7: 3.062 | C7: 2021, restoran skala menengah-besar | D7: https://databoks.katadata.co.id/ekonomi-makro/statistik/e6f7aee9363c60f/10-provinsi-dengan-restoran-skala-menengah-besar-terbanyak-di-indonesia
A8: DKI Jakarta | B8: 5.159 | C8: 2020, usaha kuliner | D8: https://goodstats.id/article/lebih-dari-10000-usaha-kuliner-ada-di-indonesia-bagaimana-statistiknya-OTIU5
A10: CATATAN:
A11: 1. Angka Jakarta saling tidak sebanding (definisi dan tahun berbeda: 3.062 vs 5.159 vs 202.983). Tidak ada satu angka yang bisa dipakai sebagai SAM Seato tanpa validasi lanjut.
A12: 2. Segmen relevan Seato (kafe/resto lifestyle yang bisa reservasi dan WFC-friendly) belum ditemukan angkanya. Plafon K Low/Mid/High di sheet Input adalah ASUMSI, bukan hasil riset.
A13: 3. Semua nilai Y2-Y5 di workbook ini adalah proyeksi dari asumsi. Y1 diambil dari tab Growth Projection file FOS (not final).
A14: 4. Churn 15%/bulan = retention 85% diartikan bulanan (konfirmasi pengguna). Jika ternyata tahunan, ubah Input!B11.
